COPYING
MANIFEST.in
NEWS
README.md
pyproject.toml
src/mix_album/__init__.py
src/mix_album/_metadata.py
src/mix_album/_mix_album.py
src/mix_album/_mix_albums.py
src/mix_album/_provider_selector.py
src/mix_album/abstract_filter.py
src/mix_album/abstract_provider.py
src/mix_album/app_context.py
src/mix_album/main.py
src/mix_album/medium.py
src/mix_album/plugin_management/__init__.py
src/mix_album/plugin_management/_plugin_loader.py
src/mix_album/plugin_management/filter_repository.py
src/mix_album/plugin_management/provider_repository.py
src/mix_album/plugins/__init__.py
src/mix_album/plugins/filters/__init__.py
src/mix_album/plugins/filters/cut.py
src/mix_album/plugins/filters/metadata.py
src/mix_album/plugins/filters/replay_gain.py
src/mix_album/plugins/providers/__init__.py
src/mix_album/plugins/providers/audio_file_provider.py
src/mix_album/plugins/providers/youtube_provider.py