Metadata-Version: 2.4
Name: mix_album
Version: 0.0.1
Summary: Utility that helps to create a custom collection of songs - a mix album.
Author-email: Róbert Čerňanský <openhs@tightmail.com>
Project-URL: Homepage, https://gitlab.com/openhs/mix_album
Classifier: Programming Language :: Python :: 3
Classifier: License :: OSI Approved :: GNU General Public License (GPL)
Classifier: Operating System :: POSIX
Requires-Python: >=3.10
License-File: COPYING
Requires-Dist: mutagen
Requires-Dist: yt_dlp
Dynamic: license-file
